uk_postcode_checker-0.1.0.dist-info/licenses/LICENSE
ukpostcode/__init__.py
ukpostcode/validator.py
uk_postcode_checker-0.1.0.dist-info/METADATA
uk_postcode_checker-0.1.0.dist-info/WHEEL
uk_postcode_checker-0.1.0.dist-info/top_level.txt
uk_postcode_checker-0.1.0.dist-info/RECORD
